{
  "schema": "ith.patient.deident/v1",
  "pseudo_id": "p_a08948370d7903ea",
  "gender": "male",
  "age_band": "70-79",
  "state": "MA",
  "conditions": [
    "Abnormal findings diagnostic imaging heart+coronary circulat (finding)",
    "Acute bronchitis (disorder)",
    "Acute non-ST segment elevation myocardial infarction (disorder)",
    "Anemia (disorder)",
    "Body mass index 30+ - obesity (finding)",
    "Chronic low back pain (finding)",
    "Chronic pain (finding)",
    "Chronic sinusitis (disorder)",
    "Full-time employment (finding)",
    "Gingivitis (disorder)",
    "Has a criminal record (finding)",
    "History of myocardial infarction (situation)",
    "Ischemic heart disease (disorder)",
    "Limited social contact (finding)",
    "Medication review due (situation)",
    "Not in labor force (finding)",
    "Part-time employment (finding)",
    "Prediabetes (finding)",
    "Received higher education (finding)",
    "Refugee (person)",
    "Reports of violence in the environment (finding)",
    "Sepsis (disorder)",
    "Severe anxiety (panic) (finding)",
    "Social isolation (finding)",
    "Sprain (morphologic abnormality)",
    "Sprain of wrist (disorder)",
    "Stress (finding)",
    "Unemployed (finding)"
  ]
}